Metadata-Version: 1.1
Name: django-transmeta
Version: 0.7.3
Summary: Transmeta is an application for translatable content in Django's models.
Home-page: https://github.com/Yaco-Sistemas/django-transmeta
Author: Yaco Sistemas S.L.
Author-email: garcia.marc@gmail.com
License: LGPL 3
Keywords: django,translation,internationalization,i18n,transmeta,models,translation models
Platform: UNKNOWN
Classifier: Development Status :: 4 - Beta
Classifier: Framework :: Django
Classifier: License :: OSI Approved :: GNU Library or Lesser General Public License (LGPL)
Classifier: Programming Language :: Python :: 2
Classifier: Programming Language :: Python :: 3
